MANIFEST.in
README.rst
setup.py
collective/__init__.py
collective.geo.flexitopic.egg-info/PKG-INFO
collective.geo.flexitopic.egg-info/SOURCES.txt
collective.geo.flexitopic.egg-info/dependency_links.txt
collective.geo.flexitopic.egg-info/entry_points.txt
collective.geo.flexitopic.egg-info/namespace_packages.txt
collective.geo.flexitopic.egg-info/not-zip-safe
collective.geo.flexitopic.egg-info/requires.txt
collective.geo.flexitopic.egg-info/top_level.txt
collective/geo/__init__.py
collective/geo/flexitopic/README.txt
collective/geo/flexitopic/__init__.py
collective/geo/flexitopic/configure.zcml
collective/geo/flexitopic/interfaces.py
collective/geo/flexitopic/profile.py
collective/geo/flexitopic/setuphandlers.py
collective/geo/flexitopic/tests.py
collective/geo/flexitopic/version.txt
collective/geo/flexitopic/browser/__init__.py
collective/geo/flexitopic/browser/configure.zcml
collective/geo/flexitopic/browser/flexitopicview.py
collective/geo/flexitopic/browser/formviewlet.pt
collective/geo/flexitopic/browser/kmlview.py
collective/geo/flexitopic/browser/map_viewlet.pt
collective/geo/flexitopic/browser/maplayer.py
collective/geo/flexitopic/locales/collective.geo.flexitopic.pot
collective/geo/flexitopic/locales/rebuild.sh
collective/geo/flexitopic/locales/es/LC_MESSAGES/collective.geo.flexitopic.mo
collective/geo/flexitopic/locales/es/LC_MESSAGES/collective.geo.flexitopic.po
collective/geo/flexitopic/portlets/__init__.py
collective/geo/flexitopic/portlets/configure.zcml
collective/geo/flexitopic/portlets/fleximapportlet.py
collective/geo/flexitopic/portlets/maplayer.py
collective/geo/flexitopic/portlets/viewlets.py
collective/geo/flexitopic/profiles/default/browserlayer.xml
collective/geo/flexitopic/profiles/default/metadata.xml
collective/geo/flexitopic/profiles/default/portlets.xml
collective/geo/flexitopic/profiles/default/viewlets.xml
collective/geo/flexitopic/profiles/default/types/Collection.xml
collective/geo/flexitopic/profiles/default/types/Topic.xml
collective/geo/flexitopic/tests/__init__.py
collective/geo/flexitopic/tests/base_fleximapportlet.py
collective/geo/flexitopic/tests/test_fleximapportlet.py
docs/HISTORY.txt
docs/INSTALL.txt
docs/LICENSE.txt